trytond/modules/health_socioeconomics/COPYING
trytond/modules/health_socioeconomics/README.rst
trytond/modules/health_socioeconomics/__init__.py
trytond/modules/health_socioeconomics/data/gnuhealth_commands.xml
trytond/modules/health_socioeconomics/health_socioeconomics.py
trytond/modules/health_socioeconomics/health_socioeconomics_view.xml
trytond/modules/health_socioeconomics/locale/ar.po
trytond/modules/health_socioeconomics/locale/de.po
trytond/modules/health_socioeconomics/locale/el.po
trytond/modules/health_socioeconomics/locale/eo.po
trytond/modules/health_socioeconomics/locale/es.po
trytond/modules/health_socioeconomics/locale/fr.po
trytond/modules/health_socioeconomics/locale/health_socioeconomics.pot
trytond/modules/health_socioeconomics/locale/it_IT.po
trytond/modules/health_socioeconomics/locale/ja_JP.po
trytond/modules/health_socioeconomics/locale/ka.po
trytond/modules/health_socioeconomics/locale/lo.po
trytond/modules/health_socioeconomics/locale/pt_BR.po
trytond/modules/health_socioeconomics/locale/sv.po
trytond/modules/health_socioeconomics/locale/tr.po
trytond/modules/health_socioeconomics/locale/uk.po
trytond/modules/health_socioeconomics/locale/zh_CN.po
trytond/modules/health_socioeconomics/pyproject.toml
trytond/modules/health_socioeconomics/security/access_rights.xml
trytond/modules/health_socioeconomics/tests/__init__.py
trytond/modules/health_socioeconomics/tests/test_health_socioeconomics.py
trytond/modules/health_socioeconomics/tryton.cfg
trytond/modules/health_socioeconomics/view/gnuhealth_patient.xml
trytond/modules/health_socioeconomics/view/gnuhealth_ses_assessment_form.xml
trytond/modules/health_socioeconomics/view/gnuhealth_ses_assessment_tree.xml
trytond/modules/health_socioeconomics/view/party_form.xml
gnuhealth_socioeconomics-5.0.2.dist-info/METADATA
gnuhealth_socioeconomics-5.0.2.dist-info/WHEEL
gnuhealth_socioeconomics-5.0.2.dist-info/licenses/COPYING
gnuhealth_socioeconomics-5.0.2.dist-info/RECORD
